pymodaq_plugins_stellarnet/VERSION
pymodaq_plugins_stellarnet/__init__.py
pymodaq_plugins_stellarnet/daq_move_plugins/__init__.py
pymodaq_plugins_stellarnet/daq_viewer_plugins/__init__.py
pymodaq_plugins_stellarnet/daq_viewer_plugins/plugins_0D/__init__.py
pymodaq_plugins_stellarnet/daq_viewer_plugins/plugins_1D/__init__.py
pymodaq_plugins_stellarnet/daq_viewer_plugins/plugins_1D/daq_1Dviewer_Stellarnet.py
pymodaq_plugins_stellarnet/daq_viewer_plugins/plugins_2D/__init__.py
pymodaq_plugins_stellarnet/daq_viewer_plugins/plugins_ND/__init__.py
pymodaq_plugins_stellarnet/extension/__init__.py
pymodaq_plugins_stellarnet/hardware/MyCaL-C20111832-VIS-IC2.CAL
pymodaq_plugins_stellarnet/hardware/__init__.py
pymodaq_plugins_stellarnet/hardware/stellarnet.hex
pymodaq_plugins_stellarnet/hardware/stellarnet.py
pymodaq_plugins_stellarnet/models/__init__.py
pymodaq_plugins_stellarnet-5.1.1.dist-info/licenses/LICENSE
pymodaq_plugins_stellarnet-5.1.1.dist-info/METADATA
pymodaq_plugins_stellarnet-5.1.1.dist-info/WHEEL
pymodaq_plugins_stellarnet-5.1.1.dist-info/entry_points.txt
pymodaq_plugins_stellarnet-5.1.1.dist-info/top_level.txt
pymodaq_plugins_stellarnet-5.1.1.dist-info/RECORD
